{
  "vnts_endpoint": "192.168.1.2:29872",
  "vnts_allowed_ips": "10.26.0.0/24",
  "group_id": "awe",
  "device_id": "wg1751429684421",
  "ip": "10.26.0.2",
  "prefix": 24,
  "persistent_keepalive": 10,
  "secret_key": [
    253,
    173,
    164,
    210,
    125,
    218,
    54,
    225,
    107,
    219,
    14,
    233,
    44,
    77,
    127,
    73,
    25,
    11,
    19,
    89,
    208,
    199,
    233,
    252,
    71,
    142,
    60,
    240,
    209,
    216,
    163,
    173
  ],
  "public_key": [
    167,
    132,
    10,
    233,
    13,
    23,
    132,
    17,
    61,
    34,
    15,
    203,
    245,
    118,
    128,
    243,
    5,
    147,
    206,
    48,
    129,
    67,
    190,
    71,
    193,
    88,
    156,
    76,
    67,
    146,
    85,
    32
  ]
}